LICENSE
README.md
nautobot_ssot_aci/__init__.py
nautobot_ssot_aci/constant.py
nautobot_ssot_aci/diffsync/__init__.py
nautobot_ssot_aci/diffsync/adapters/__init__.py
nautobot_ssot_aci/diffsync/adapters/aci.py
nautobot_ssot_aci/diffsync/adapters/nautobot.py
nautobot_ssot_aci/diffsync/client.py
nautobot_ssot_aci/diffsync/device-types/APIC-SERVER-L2.yaml
nautobot_ssot_aci/diffsync/device-types/APIC-SERVER-L3.yaml
nautobot_ssot_aci/diffsync/device-types/APIC-SERVER-M1.yaml
nautobot_ssot_aci/diffsync/device-types/APIC-SERVER-M3.yaml
nautobot_ssot_aci/diffsync/device-types/APIC-SIM.yaml
nautobot_ssot_aci/diffsync/device-types/N2K-C2232PP-10GE.yaml
nautobot_ssot_aci/diffsync/device-types/N2K-C2232TM-10GE.yaml
nautobot_ssot_aci/diffsync/device-types/N2K-C2232TM-E-10GE.yaml
nautobot_ssot_aci/diffsync/device-types/N2K-C2248PQ-10GE.yaml
nautobot_ssot_aci/diffsync/device-types/N2K-C2248TP-1GE.yaml
nautobot_ssot_aci/diffsync/device-types/N2K-C2248TP-E-1GE.yaml
nautobot_ssot_aci/diffsync/device-types/N2K-C2348TQ-10GE.yaml
nautobot_ssot_aci/diffsync/device-types/N2K-C2348UPQ-10GE.yaml
nautobot_ssot_aci/diffsync/device-types/N9K-C93108LC-EX.yaml
nautobot_ssot_aci/diffsync/device-types/N9K-C93108TC-EX.yaml
nautobot_ssot_aci/diffsync/device-types/N9K-C93108TC-FX.yaml
nautobot_ssot_aci/diffsync/device-types/N9K-C93120TX.yaml
nautobot_ssot_aci/diffsync/device-types/N9K-C93180LC-EX.yaml
nautobot_ssot_aci/diffsync/device-types/N9K-C93180YC-EX.yaml
nautobot_ssot_aci/diffsync/device-types/N9K-C93180YC-FX.yaml
nautobot_ssot_aci/diffsync/device-types/N9K-C9332C.yaml
nautobot_ssot_aci/diffsync/device-types/N9K-C9336C-FX2.yaml
nautobot_ssot_aci/diffsync/device-types/N9K-C9336PQ.yaml
nautobot_ssot_aci/diffsync/device-types/N9K-C9372PX-TX.yaml
nautobot_ssot_aci/diffsync/device-types/N9K-C9396PX.yaml
nautobot_ssot_aci/diffsync/device-types/N9K-C9508.yaml
nautobot_ssot_aci/diffsync/device-types/VMware Virtual Platform.yaml
nautobot_ssot_aci/diffsync/models/__init__.py
nautobot_ssot_aci-1.0.0.dist-info/LICENSE
nautobot_ssot_aci-1.0.0.dist-info/WHEEL
nautobot_ssot_aci-1.0.0.dist-info/METADATA
nautobot_ssot_aci-1.0.0.dist-info/RECORD
