Metadata-Version: 2.1
Name: nautobot-ssot-aci
Version: 1.0.0
Summary: Nautobot SSoT for Cisco ACI
Home-page: https://github.com/nautobot/nautobot-plugin-ssot-aci
License: Apache-2.0
Keywords: nautobot,nautobot-plugin
Author: Network to Code, LLC
Author-email: info@networktocode.com
Requires-Python: >=3.7,<4.0
Classifier: License :: OSI Approved :: Apache Software License
Classifier: Programming Language :: Python :: 3
Classifier: Programming Language :: Python :: 3.10
Classifier: Programming Language :: Python :: 3.7
Classifier: Programming Language :: Python :: 3.8
Classifier: Programming Language :: Python :: 3.9
Provides-Extra: nautobot
Requires-Dist: Jinja2 (<3)
Requires-Dist: PyYAML (>=5.4.1,<6.0.0)
Requires-Dist: diffsync (>=1.3.0,<2.0.0)
Requires-Dist: nautobot (>=1.2.5,<2.0.0); extra == "nautobot"
Requires-Dist: nautobot-ssot (>=1.0.1,<2.0.0)
Project-URL: Repository, https://github.com/nautobot/nautobot-plugin-ssot-aci
